philsol/__init__.py
philsol/classy.py
philsol/construct.py
philsol/core.py
philsol/solve.py
philsol-0.25.dist-info/WHEEL
philsol-0.25.dist-info/METADATA
philsol-0.25.dist-info/RECORD
