Metadata-Version: 2.1
Name: philsol
Version: 0.25
Summary: A fully vectorial finite difference waveguide mode solver. Based on the algorithm of Zhu and Brown
Home-page: https://github.com/philmain28/philsol
License: GNU GPL
Keywords: vector,finite difference,waveguide,mode solver
Author: Phil Main
Author-email: philmain28@gmail.com
Requires-Python: >=3.5,<4.0
Classifier: License :: Other/Proprietary License
Classifier: Programming Language :: Python :: 3
Classifier: Programming Language :: Python :: 3.5
Classifier: Programming Language :: Python :: 3.6
Classifier: Programming Language :: Python :: 3.7
Classifier: Programming Language :: Python :: 3.8
Classifier: Programming Language :: Python :: 3.9
Requires-Dist: numpy (>=1.17,<2.0)
Requires-Dist: scipy (>=1.3,<2.0)
Project-URL: Repository, https://github.com/philmain28/philsol
